kaling/KakaoModule.py
kaling/__init__.py
kaling-0.3.0.dist-info/LICENSE
kaling-0.3.0.dist-info/METADATA
kaling-0.3.0.dist-info/WHEEL
kaling-0.3.0.dist-info/top_level.txt
kaling-0.3.0.dist-info/RECORD
