Metadata-Version: 2.1
Name: kaling
Version: 0.3.0
Summary: pure python library for sending kakaolinks
Home-page: https://github.com/idev-develop/KakaoLink-Python
Author: andyyeyeye
Author-email: andyye.jongcye@gmail.com
License: MIT License
Platform: UNKNOWN
Requires-Dist: requests
Requires-Dist: bs4
Requires-Dist: pycryptodome
